mcp_pandoc/__init__.py
mcp_pandoc/server.py
iflow_mcp_mcp_pandoc-0.5.0.dist-info/METADATA
iflow_mcp_mcp_pandoc-0.5.0.dist-info/WHEEL
iflow_mcp_mcp_pandoc-0.5.0.dist-info/entry_points.txt
iflow_mcp_mcp_pandoc-0.5.0.dist-info/licenses/LICENSE
iflow_mcp_mcp_pandoc-0.5.0.dist-info/RECORD
